dwl.py
dwl-0.4.1.data/scripts/dwl
dwl-0.4.1.dist-info/METADATA
dwl-0.4.1.dist-info/WHEEL
dwl-0.4.1.dist-info/top_level.txt
dwl-0.4.1.dist-info/RECORD
